lightweight_chess_engine/__init__.py
lightweight_chess_engine/engine.py
lightweight_chess_engine/binaries/bbc_1_engin
lightweight_chess_engine-0.1.1.dist-info/LICENSE
lightweight_chess_engine-0.1.1.dist-info/METADATA
lightweight_chess_engine-0.1.1.dist-info/WHEEL
lightweight_chess_engine-0.1.1.dist-info/top_level.txt
lightweight_chess_engine-0.1.1.dist-info/RECORD
