Metadata-Version: 2.1
Name: lightweight-chess-engine
Version: 0.1.1
Summary: A lightweight chess engine library for Linux.
Author: Lecheheb djaafar
Author-email: djaafardjaafarlolo@gmail.com
Classifier: Programming Language :: Python :: 3
Classifier: Operating System :: POSIX :: Linux
Requires-Python: >=3.6
License-File: LICENSE
